EasyWorkEnv/__init__.py
EasyWorkEnv/config.py
easyworkenv-0.3.5.dist-info/licenses/LICENSE
easyworkenv-0.3.5.dist-info/METADATA
easyworkenv-0.3.5.dist-info/WHEEL
easyworkenv-0.3.5.dist-info/top_level.txt
easyworkenv-0.3.5.dist-info/RECORD
