Metadata-Version: 2.4
Name: easyworkenv
Version: 0.3.5
Summary: This is a package that simplifies environment variable management.
Author-email: Galley Hugo <galleyhugo@icloud.com>
License: GPL-3.0-or-later
Project-URL: HomePage, https://github.com/Hugo-Galley/EasyWorkEnv
Requires-Python: >=3.8
License-File: LICENSE
Requires-Dist: PyYAML>=6.0.2
Dynamic: license-file
